arrowbit/__init__.py
arrowbit/repl.py
arrowbit/ext/cogs.py
arrowbit/ext/commands.py
arrowbit/ext/core.py
arrowbit/ext/errors.py
arrowbit/ext/parser.py
arrowbit/ext/runtime.py
arrowbit/ext/utils.py
arrowbit-0.1.2.dist-info/licenses/LICENSE
arrowbit-0.1.2.dist-info/METADATA
arrowbit-0.1.2.dist-info/WHEEL
arrowbit-0.1.2.dist-info/top_level.txt
arrowbit-0.1.2.dist-info/RECORD
